getproxies/__init__.py
getproxies/cli.py
getproxies/proxies.py
getproxies/proxy.py
getproxies/spiders/__init__.py
getproxies/spiders/base.py
getproxies/spiders/freeproxylist.py
getproxies/spiders/proxydaily.py
getproxies-1.0.0.dist-info/entry_points.txt
getproxies-1.0.0.dist-info/WHEEL
getproxies-1.0.0.dist-info/METADATA
getproxies-1.0.0.dist-info/RECORD
