Metadata-Version: 2.1
Name: getproxies
Version: 1.0.0
Summary: Scraper of free online proxies
Home-page: https://github.com/granitosaurus/getproxies
License: LGPL-3.0-or-later
Keywords: proxies,web-crawling,cli
Author: granitosaurus
Author-email: bernardas.alisauskas@pm.me
Requires-Python: >=3.6,<4.0
Classifier: License :: OSI Approved :: GNU Lesser General Public License v3 or later (LGPLv3+)
Classifier: Programming Language :: Python :: 3
Classifier: Programming Language :: Python :: 3.6
Classifier: Programming Language :: Python :: 3.7
Classifier: Programming Language :: Python :: 3.8
Requires-Dist: click (>=7.1.1,<8.0.0)
Requires-Dist: parsel (>=1.5.2,<2.0.0)
Requires-Dist: requests (>=2.22.0,<3.0.0)
Project-URL: Repository, https://github.com/granitosaurus/getproxies
